smpl_rs-0.7.0.dist-info/METADATA
smpl_rs-0.7.0.dist-info/WHEEL
smpl_rs/codec.pyi
smpl_rs/plugins.pyi
smpl_rs/components.pyi
smpl_rs/types.pyi
smpl_rs/__pycache__/__init__.cpython-38.pyc
smpl_rs/__init__.pyi
smpl_rs/models.pyi
smpl_rs/__init__.py
smpl_rs/py.typed
smpl_rs/builders.pyi
smpl_rs/smpl_rs.pypy39-pp73-win_amd64.pyd
smpl_rs-0.7.0.dist-info/RECORD
