Metadata-Version: 2.4
Name: smpl_rs
Version: 0.7.0
Requires-Dist: gloss-rs >=0.5.0 ; extra == 'gloss'
Provides-Extra: gloss
Summary: A suite of SMPL functionality written over gloss
Author: Radu Alexandru Rosu <alex@meshcapade.com>, Aman Shenoy <aman@meshcapade.com>
Author-email: Radu Alexandru Rosu <alex@meshcapade.com>, Aman Shenoy <aman@meshcapade.com>
License: MIT
Requires-Python: >=3.8
